graphmlp_flax/__init__.py
graphmlp_flax/models.py
graphmlp_flax-0.0.1.dist-info/LICENSE
graphmlp_flax-0.0.1.dist-info/METADATA
graphmlp_flax-0.0.1.dist-info/WHEEL
graphmlp_flax-0.0.1.dist-info/top_level.txt
graphmlp_flax-0.0.1.dist-info/zip-safe
graphmlp_flax-0.0.1.dist-info/RECORD
