Metadata-Version: 2.1
Name: graphmlp-flax
Version: 0.0.1
Summary: Minimal Flax Implementation of Graph-MLP: Node Classification without Message Passing in Graph
Home-page: https://github.com/SauravMaheshkar/GraphMLP-Flax
Author: Saurav Maheshkar
Author-email: sauravvmaheshkar@gmail.com
License: MIT
Platform: UNKNOWN
Requires-Dist: flax
Requires-Dist: jax
